gcvit/__init__.py
gcvit/version.py
gcvit/layers/__init__.py
gcvit/layers/attention.py
gcvit/layers/block.py
gcvit/layers/drop.py
gcvit/layers/embedding.py
gcvit/layers/feature.py
gcvit/layers/level.py
gcvit/layers/pooling.py
gcvit/layers/window.py
gcvit/models/__init__.py
gcvit/models/gcvit.py
gcvit/utils/__init__.py
gcvit/utils/conv_utils.py
gcvit/utils/gradcam.py
gcvit-1.1.6.dist-info/LICENSE.md
gcvit-1.1.6.dist-info/METADATA
gcvit-1.1.6.dist-info/WHEEL
gcvit-1.1.6.dist-info/top_level.txt
gcvit-1.1.6.dist-info/RECORD
