Metadata-Version: 2.1
Name: gcvit
Version: 1.1.6
Summary: Tensorflow 2.0 Implementation of GCViT: Global Context Vision Transformer. https://github.com/awsaf49/gcvit-tf
Home-page: https://github.com/awsaf49/gcvit-tf
Author: Awsaf
Author-email: awsaf49@gmail.com
License: MIT
Keywords: tensorflow computer_vision image classification transformer
Classifier: Development Status :: 3 - Alpha
Classifier: Intended Audience :: Developers
Classifier: Intended Audience :: Science/Research
Classifier: License :: OSI Approved :: Apache Software License
Classifier: Programming Language :: Python :: 3.6
Classifier: Programming Language :: Python :: 3.7
Classifier: Programming Language :: Python :: 3.8
Classifier: Topic :: Scientific/Engineering
Classifier: Topic :: Scientific/Engineering :: Artificial Intelligence
Classifier: Topic :: Software Development
Classifier: Topic :: Software Development :: Libraries
Classifier: Topic :: Software Development :: Libraries :: Python Modules
Requires-Python: >=3.6
License-File: LICENSE.md
Requires-Dist: typing
Requires-Dist: gradio
Requires-Dist: numpy
Requires-Dist: matplotlib
